pg_asynq/AsynqManager.py
pg_asynq/AsynqMessage.py
pg_asynq/__init__.py
pg_asynq-0.2.0.dist-info/LICENSE.md
pg_asynq-0.2.0.dist-info/METADATA
pg_asynq-0.2.0.dist-info/WHEEL
pg_asynq-0.2.0.dist-info/RECORD
