Metadata-Version: 2.1
Name: pg_asynq
Version: 0.2.0
Summary: Barebones async-powered message queue on python with psycopg (v3)
Home-page: https://github.com/amithkk/pg-asynq
License: MIT
Author: Amith K K
Author-email: amithkumaran@gmail.com
Requires-Python: >=3.11,<4.0
Classifier: License :: OSI Approved :: MIT License
Classifier: Programming Language :: Python :: 3
Classifier: Programming Language :: Python :: 3.11
Classifier: Programming Language :: Python :: 3.12
Classifier: Programming Language :: Python :: 3.13
Classifier: Topic :: Database
Requires-Dist: orjson (>=3.10.12,<4.0.0)
Requires-Dist: psycopg[pool] (>=3.2.3,<4.0.0)
Project-URL: Repository, https://github.com/amithkk/pg-asynq
